ofxstatement_fineco/__init__.py
ofxstatement_fineco/plugin.py
ofxstatement_fineco/config/defaults.ini
ofxstatement_fineco-0.1.2.dist-info/METADATA
ofxstatement_fineco-0.1.2.dist-info/WHEEL
ofxstatement_fineco-0.1.2.dist-info/entry_points.txt
ofxstatement_fineco-0.1.2.dist-info/top_level.txt
ofxstatement_fineco-0.1.2.dist-info/RECORD
