Metadata-Version: 2.1
Name: ofxstatement-fineco
Version: 0.1.2
Summary: italian bank Fineco, it parses both xls files available for private accounts
Author: Francesco Lorenzetti
Project-URL: Homepage, https://github.com/frankIT/ofxstatement-fineco
Keywords: ofx,banking,statement,plugin,ofxstatement,fineco
Classifier: Development Status :: 3 - Alpha
Classifier: Programming Language :: Python :: 3
Classifier: Natural Language :: English
Classifier: Topic :: Office/Business :: Financial :: Accounting
Classifier: Topic :: Utilities
Classifier: Environment :: Console
Classifier: Operating System :: OS Independent
Classifier: License :: OSI Approved :: GNU General Public License v3 (GPLv3)
Requires-Python: >=3.9
Requires-Dist: ofxstatement
Requires-Dist: xlrd<=1.2.0
